netective/__init__.py
netective/implementation.py
netective-0.0.2.dist-info/METADATA
netective-0.0.2.dist-info/WHEEL
netective-0.0.2.dist-info/entry_points.txt
netective-0.0.2.dist-info/top_level.txt
netective-0.0.2.dist-info/RECORD
