Metadata-Version: 2.1
Name: netective
Version: 0.0.2
Summary: Use structural and standard performance metrics to assess network inference
Author-email: Juan Escorcia <juanesscorcia@gmail.com>, Julio Freyre <jfreyreg@gmail.com>
Project-URL: Homepage, https://github.com/JuanEscorcia/netective.git
Classifier: Programming Language :: Python :: 3
Classifier: License :: OSI Approved :: MIT License
Classifier: Operating System :: OS Independent
Requires-Python: >=3.7
Provides-Extra: cov
Requires-Dist: pytest (<5.0.0) ; extra == 'cov'
Requires-Dist: pytest-cov[all] ; extra == 'cov'
Provides-Extra: lint
Requires-Dist: black ; extra == 'lint'
Provides-Extra: test
Requires-Dist: pytest ; extra == 'test'
